MANIFEST.in
README.txt
setup.cfg
setup.py
docs/HISTORY.txt
docs/INSTALL.txt
docs/LICENSE.GPL
docs/LICENSE.txt
docs/TEST.txt
docs/TODO.txt
ilrt/__init__.py
ilrt.contentmigrator.egg-info/PKG-INFO
ilrt.contentmigrator.egg-info/SOURCES.txt
ilrt.contentmigrator.egg-info/dependency_links.txt
ilrt.contentmigrator.egg-info/entry_points.txt
ilrt.contentmigrator.egg-info/namespace_packages.txt
ilrt.contentmigrator.egg-info/not-zip-safe
ilrt.contentmigrator.egg-info/requires.txt
ilrt.contentmigrator.egg-info/top_level.txt
ilrt/contentmigrator/__init__.py
ilrt/contentmigrator/configure.zcml
ilrt/contentmigrator/profiles.zcml
ilrt/contentmigrator/run_import.py
ilrt/contentmigrator/tool.png
ilrt/contentmigrator/version.txt
ilrt/contentmigrator/ContentMigrator/ContentExporter.py
ilrt/contentmigrator/ContentMigrator/README.txt
ilrt/contentmigrator/ContentMigrator/__init__.py
ilrt/contentmigrator/ContentMigrator/config.py
ilrt/contentmigrator/ContentMigrator/interfaces.py
ilrt/contentmigrator/ContentMigrator/refresh.txt
ilrt/contentmigrator/ContentMigrator/tool.gif
ilrt/contentmigrator/ContentMigrator/version.txt
ilrt/contentmigrator/ContentMigrator/Extensions/.cvsignore
ilrt/contentmigrator/ContentMigrator/Extensions/Install.py
ilrt/contentmigrator/ContentMigrator/www/explainContentMigrator.pt
ilrt/contentmigrator/ContentMigrator/www/exportContentMigrator.pt
ilrt/contentmigrator/ContentMigrator/xml/zodbgroups.xml.dtml
ilrt/contentmigrator/ContentMigrator/xml/zodbroles.xml.dtml
ilrt/contentmigrator/ContentMigrator/xml/zodbusers.xml.dtml
ilrt/contentmigrator/browser/__init__.py
ilrt/contentmigrator/browser/__init__.pyo
ilrt/contentmigrator/browser/configure.zcml
ilrt/contentmigrator/browser/contentmigratortool.py
ilrt/contentmigrator/browser/interfaces.py
ilrt/contentmigrator/browser/templates/explainContentMigrator.pt
ilrt/contentmigrator/browser/templates/exportContentMigrator.pt
ilrt/contentmigrator/browser/templates/importContentMigrator.pt
ilrt/contentmigrator/exportimport/__init__.py
ilrt/contentmigrator/exportimport/configure.zcml
ilrt/contentmigrator/exportimport/content.py
ilrt/contentmigrator/exportimport/contentexporter.py
ilrt/contentmigrator/exportimport/exportContentMigrator.pt
ilrt/contentmigrator/exportimport/pas.py
ilrt/contentmigrator/exportimport/utils.py
ilrt/contentmigrator/google/README.txt
