Metadata-Version: 1.1
Name: ilrt.contentmigrator
Version: 1.14
Summary: Migrate old Plone or Google Sites content to current Plone 4
Home-page: http://bitbucket.org/edcrewe/ilrt.contentmigrator
Author: Internet Development, ILRT, University of Bristol
Author-email: internet-development@bris.ac.uk
License: GPL
Keywords: web zope plone migration setup release management workflow
Platform: UNKNOWN
Classifier: Programming Language :: Python
Classifier: Topic :: Software Development :: Libraries :: Python Modules
Classifier: Environment :: Web Environment
Classifier: Framework :: Plone
Classifier: Framework :: Zope2
Classifier: Framework :: Zope3
Classifier: Intended Audience :: Developers
Classifier: Intended Audience :: Other Audience
Classifier: License :: OSI Approved :: BSD License
Classifier: Operating System :: OS Independent
Classifier: Development Status :: 4 - Beta
